trustedtwin_utils/__init__.py
trustedtwin_utils/epoch/__init__.py
trustedtwin_utils/epoch/tt_epoch.py
trustedtwin_utils/identity/__init__.py
trustedtwin_utils/identity/hashed_id.py
trustedtwin_utils/json/__init__.py
trustedtwin_utils/json/tt_signed_json.py
trustedtwin_utils/models/__init__.py
trustedtwin_utils/models/tt_subcodes.py
trustedtwin_utils/models/responses/__init__.py
trustedtwin_utils/models/responses/tt_exception.py
trustedtwin_utils-0.1.20240802101620.dist-info/METADATA
trustedtwin_utils-0.1.20240802101620.dist-info/WHEEL
trustedtwin_utils-0.1.20240802101620.dist-info/top_level.txt
trustedtwin_utils-0.1.20240802101620.dist-info/RECORD
