Metadata-Version: 2.1
Name: trustedtwin_utils
Version: 0.1.20240802101620
Summary: Trusted Twin utils library
Home-page: https://gitlab.com/trustedtwinpublic/trusted-twin-utils
Author: Trusted Twin
License: MIT
Requires-Python: >=3.9
Requires-Dist: pydantic <3,>=2
